immich_lib/__init__.py
immich_lib/base.py
immich_lib/cli.py
immich_lib/client.py
immich_lib/api/activities.py
immich_lib/api/albums.py
immich_lib/api/assets.py
immich_lib/api/folders.py
immich_lib/api/jobs.py
immich_lib/api/misc.py
immich_lib/api/partners.py
immich_lib/api/people.py
immich_lib/api/search.py
immich_lib/api/stacks.py
immich_lib/api/system.py
immich_lib/api/tags.py
immich_lib/api/trash.py
immich_lib/api/users.py
immich_lib-0.2.1.dist-info/METADATA
immich_lib-0.2.1.dist-info/WHEEL
immich_lib-0.2.1.dist-info/entry_points.txt
immich_lib-0.2.1.dist-info/top_level.txt
immich_lib-0.2.1.dist-info/RECORD
