Metadata-Version: 2.4
Name: immich-lib
Version: 0.2.1
Summary: A Python library and CLI tool for interacting with Immich
Author: guanana
License: MIT
Project-URL: Homepage, https://github.com/guanana/immich-lib
Project-URL: Bug Tracker, https://github.com/guanana/immich-lib/issues
Keywords: immich,api,cli,photos
Classifier: Programming Language :: Python :: 3
Classifier: License :: OSI Approved :: MIT License
Classifier: Operating System :: OS Independent
Classifier: Topic :: Multimedia :: Graphics
Classifier: Topic :: Software Development :: Libraries :: Python Modules
Requires-Python: >=3.7
Requires-Dist: requests
Requires-Dist: python-dotenv
Requires-Dist: tqdm
